Metadata-Version: 2.1
Name: blacker
Version: 0.1.0
Summary: The uncompromising code formatter that respects PEP8.
Home-page: https://github.com/stefanoborini/blacker
Author: Stefano Borini
Author-email: stefano.borini@gmail.com
License: MIT
Keywords: automation formatter yapf autopep8 pyfmt gofmt rustfmt
Platform: UNKNOWN
Classifier: Development Status :: 4 - Beta
Classifier: Environment :: Console
Classifier: Intended Audience :: Developers
Classifier: License :: OSI Approved :: MIT License
Classifier: Operating System :: OS Independent
Classifier: Programming Language :: Python
Classifier: Programming Language :: Python :: 3.6
Classifier: Programming Language :: Python :: 3.7
Classifier: Programming Language :: Python :: 3.8
Classifier: Programming Language :: Python :: 3 :: Only
Classifier: Topic :: Software Development :: Libraries :: Python Modules
Classifier: Topic :: Software Development :: Quality Assurance
Requires-Python: >=3.6
Provides-Extra: d
